latex_pdf_size_optimizer/__init__.py
latex_pdf_size_optimizer/cli.py
latex_pdf_size_optimizer/core.py
latex_pdf_size_optimizer-0.1.1.dist-info/METADATA
latex_pdf_size_optimizer-0.1.1.dist-info/WHEEL
latex_pdf_size_optimizer-0.1.1.dist-info/entry_points.txt
latex_pdf_size_optimizer-0.1.1.dist-info/top_level.txt
latex_pdf_size_optimizer-0.1.1.dist-info/RECORD
