Metadata-Version: 2.4
Name: latex-pdf-size-optimizer
Version: 0.1.1
Summary: A tool to optimize LaTeX projects by converting images and compressing PDFs.
Author-email: Stival <stival@example.com>
Project-URL: Homepage, https://github.com/example/latex-optimizer
Classifier: Programming Language :: Python :: 3
Classifier: License :: OSI Approved :: MIT License
Classifier: Operating System :: OS Independent
Requires-Python: >=3.7
Requires-Dist: tqdm
Requires-Dist: Pillow
Requires-Dist: tomli>=2.0.0; python_version < "3.11"
